accfg/__init__.py
accfg/compare.py
accfg/draw.py
accfg/fgs_common.csv
accfg/fgs_heterocycle.csv
accfg/main.py
accfg-0.0.9.dist-info/licenses/LICENSE
accfg-0.0.9.dist-info/METADATA
accfg-0.0.9.dist-info/WHEEL
accfg-0.0.9.dist-info/top_level.txt
accfg-0.0.9.dist-info/RECORD
