Metadata-Version: 2.4
Name: accfg
Version: 0.0.9
Summary: AccFG: Molecule functional group extraction and molecular structure comparison
Author-email: Xuan Liu <xliu254@illinois.edu>
Project-URL: Homepage, https://github.com/xuanliugit/AccFG
Requires-Python: >=3.10
License-File: LICENSE
Requires-Dist: matplotlib>=3.10.1
Requires-Dist: networkx>=3.3.1
Requires-Dist: numpy>=2.2.4
Requires-Dist: pandas>=2.2.3
Requires-Dist: Pillow>=11.1.0
Requires-Dist: rdkit>=2024.9.4
Requires-Dist: swifter>=1.4.0
Requires-Dist: tqdm
Dynamic: license-file
